dataqruiser/__init__.py
dataqruiser-0.0.1.dist-info/LICENCE
dataqruiser-0.0.1.dist-info/METADATA
dataqruiser-0.0.1.dist-info/WHEEL
dataqruiser-0.0.1.dist-info/top_level.txt
dataqruiser-0.0.1.dist-info/zip-safe
dataqruiser-0.0.1.dist-info/RECORD
